brokle/__init__.py
brokle/_base_client.py
brokle/_client.py
brokle/config.py
brokle/decorators.py
brokle/evaluate.py
brokle/exporter.py
brokle/hooks.py
brokle/integration.py
brokle/masking_exporter.py
brokle/processor.py
brokle/version.py
brokle/_http/__init__.py
brokle/_http/client.py
brokle/_utils/__init__.py
brokle/_utils/sync.py
brokle/annotations/__init__.py
brokle/annotations/_managers.py
brokle/annotations/exceptions.py
brokle/annotations/types.py
brokle/datasets/__init__.py
brokle/datasets/_managers.py
brokle/datasets/dataset.py
brokle/datasets/exceptions.py
brokle/datasets/types.py
brokle/examples/basic_usage.py
brokle/examples/langchain_integration.py
brokle/examples/llamaindex_integration.py
brokle/examples/wrapper_usage.py
brokle/experiments/__init__.py
brokle/experiments/_manager.py
brokle/experiments/exceptions.py
brokle/experiments/types.py
brokle/integrations/__init__.py
brokle/integrations/crewai.py
brokle/integrations/langchain.py
brokle/integrations/llamaindex.py
brokle/logs/__init__.py
brokle/logs/provider.py
brokle/metrics/__init__.py
brokle/metrics/constants.py
brokle/metrics/instruments.py
brokle/metrics/provider.py
brokle/observations/__init__.py
brokle/observations/types.py
brokle/observations/wrapper.py
brokle/prompts/__init__.py
brokle/prompts/_base.py
brokle/prompts/_managers.py
brokle/prompts/cache.py
brokle/prompts/compiler.py
brokle/prompts/exceptions.py
brokle/prompts/prompt.py
brokle/prompts/types.py
brokle/query/__init__.py
brokle/query/_managers.py
brokle/query/exceptions.py
brokle/query/types.py
brokle/scorers/__init__.py
brokle/scorers/base.py
brokle/scorers/base_evaluator.py
brokle/scorers/decorator.py
brokle/scorers/factuality.py
brokle/scorers/llm_scorer.py
brokle/scorers/quality.py
brokle/scorers/rag.py
brokle/scorers/relevance.py
brokle/scorers/safety.py
brokle/scores/__init__.py
brokle/scores/_managers.py
brokle/scores/exceptions.py
brokle/scores/types.py
brokle/streaming/__init__.py
brokle/streaming/accumulator.py
brokle-0.4.0.dist-info/licenses/LICENSE
brokle-0.4.0.dist-info/METADATA
brokle-0.4.0.dist-info/WHEEL
brokle-0.4.0.dist-info/top_level.txt
brokle-0.4.0.dist-info/RECORD
