Metadata-Version: 2.4
Name: brokle
Version: 0.4.0
Summary: Brokle Platform Python SDK for OpenTelemetry-native LLM observability and tracing
Author-email: Brokle Platform <support@brokle.com>
Maintainer-email: Brokle Platform <support@brokle.com>
License: MIT
Project-URL: Homepage, https://github.com/brokle-ai/brokle-python
Project-URL: Documentation, https://docs.brokle.com/sdk/python
Project-URL: Repository, https://github.com/brokle-ai/brokle-python
Project-URL: Bug Tracker, https://github.com/brokle-ai/brokle-python/issues
Project-URL: Changelog, https://github.com/brokle-ai/brokle-python/blob/main/CHANGELOG.md
Keywords: ai,llm,brokle,openai,observability,opentelemetry,tracing,wrapper,decorator,patterns
Classifier: Development Status :: 4 - Beta
Classifier: Intended Audience :: Developers
Classifier: License :: OSI Approved :: MIT License
Classifier: Programming Language :: Python :: 3
Classifier: Programming Language :: Python :: 3.9
Classifier: Programming Language :: Python :: 3.10
Classifier: Programming Language :: Python :: 3.11
Classifier: Programming Language :: Python :: 3.12
Classifier: Topic :: Software Development :: Libraries :: Python Modules
Classifier: Topic :: Scientific/Engineering :: Artificial Intelligence
Classifier: Topic :: System :: Monitoring
Requires-Python: <4.0,>=3.9
License-File: LICENSE
Requires-Dist: httpx>=0.27.0
Requires-Dist: pydantic>=2.0.0
Requires-Dist: opentelemetry-api>=1.30.0
Requires-Dist: opentelemetry-sdk>=1.30.0
Requires-Dist: opentelemetry-instrumentation>=0.50b0
Requires-Dist: opentelemetry-exporter-otlp>=1.30.0
Requires-Dist: opentelemetry-semantic-conventions>=0.50b0
Requires-Dist: opentelemetry-propagator-b3>=1.30.0
Requires-Dist: opentelemetry-propagator-jaeger>=1.30.0
Requires-Dist: opentelemetry-propagator-aws-xray>=1.0.0
Requires-Dist: typing-extensions>=4.0.0
Requires-Dist: python-dotenv>=1.0.0
Requires-Dist: backoff>=2.2.1
Requires-Dist: python-ulid>=2.0.0
Requires-Dist: chevron>=0.14.0
Requires-Dist: jinja2>=3.1.0
Provides-Extra: openai
Requires-Dist: openai<3.0.0,>=1.0.0; extra == "openai"
Requires-Dist: wrapt>=1.15.0; extra == "openai"
Provides-Extra: anthropic
Requires-Dist: anthropic>=0.30.0; extra == "anthropic"
Provides-Extra: google
Requires-Dist: google-genai>=1.0.0; extra == "google"
Provides-Extra: langchain
Requires-Dist: langchain>=0.3.0; extra == "langchain"
Requires-Dist: langchain-core>=0.3.0; extra == "langchain"
Requires-Dist: langchain-openai>=0.2.0; extra == "langchain"
Provides-Extra: llamaindex
Requires-Dist: llama-index>=0.11.0; extra == "llamaindex"
Provides-Extra: integrations
Requires-Dist: langchain>=0.3.0; extra == "integrations"
Requires-Dist: langchain-core>=0.3.0; extra == "integrations"
Requires-Dist: langchain-openai>=0.2.0; extra == "integrations"
Requires-Dist: llama-index>=0.11.0; extra == "integrations"
Provides-Extra: dev
Requires-Dist: pytest>=8.0.0; extra == "dev"
Requires-Dist: pytest-asyncio>=0.23.0; extra == "dev"
Requires-Dist: pytest-cov>=5.0.0; extra == "dev"
Requires-Dist: black>=24.0.0; extra == "dev"
Requires-Dist: isort<7.0.0,>=5.12.0; extra == "dev"
Requires-Dist: flake8>=7.0.0; extra == "dev"
Requires-Dist: mypy>=1.10.0; extra == "dev"
Requires-Dist: pre-commit>=3.8.0; extra == "dev"
Provides-Extra: docs
Requires-Dist: mkdocs>=1.6.0; extra == "docs"
Requires-Dist: mkdocs-material>=9.5.0; extra == "docs"
Requires-Dist: mkdocstrings[python]>=0.26.0; extra == "docs"
Provides-Extra: all
Requires-Dist: openai<3.0.0,>=1.0.0; extra == "all"
Requires-Dist: wrapt>=1.15.0; extra == "all"
Requires-Dist: anthropic>=0.30.0; extra == "all"
Requires-Dist: google-genai>=1.0.0; extra == "all"
Requires-Dist: langchain>=0.3.0; extra == "all"
Requires-Dist: langchain-core>=0.3.0; extra == "all"
Requires-Dist: langchain-openai>=0.2.0; extra == "all"
Requires-Dist: llama-index>=0.11.0; extra == "all"
Requires-Dist: pytest>=8.0.0; extra == "all"
Requires-Dist: pytest-asyncio>=0.23.0; extra == "all"
Requires-Dist: pytest-cov>=5.0.0; extra == "all"
Requires-Dist: black>=24.0.0; extra == "all"
Requires-Dist: isort<7.0.0,>=5.12.0; extra == "all"
Requires-Dist: flake8>=7.0.0; extra == "all"
Requires-Dist: mypy>=1.10.0; extra == "all"
Requires-Dist: pre-commit>=3.8.0; extra == "all"
Requires-Dist: mkdocs>=1.6.0; extra == "all"
Requires-Dist: mkdocs-material>=9.5.0; extra == "all"
Requires-Dist: mkdocstrings[python]>=0.26.0; extra == "all"
Dynamic: license-file
